[
  {"s": "RELIANCE", "n": "Reliance Industries"},
  {"s": "TCS", "n": "Tata Consultancy Services"},
  {"s": "HDFCBANK", "n": "HDFC Bank"},
  {"s": "ICICIBANK", "n": "ICICI Bank"},
  {"s": "INFY", "n": "Infosys"},
  {"s": "HINDUNILVR", "n": "Hindustan Unilever"},
  {"s": "ITC", "n": "ITC"},
  {"s": "SBIN", "n": "State Bank of India"},
  {"s": "BHARTIARTL", "n": "Bharti Airtel"},
  {"s": "KOTAKBANK", "n": "Kotak Mahindra Bank"},
  {"s": "LT", "n": "Larsen & Toubro"},
  {"s": "AXISBANK", "n": "Axis Bank"},
  {"s": "BAJFINANCE", "n": "Bajaj Finance"},
  {"s": "ASIANPAINT", "n": "Asian Paints"},
  {"s": "MARUTI", "n": "Maruti Suzuki"},
  {"s": "HCLTECH", "n": "HCL Technologies"},
  {"s": "SUNPHARMA", "n": "Sun Pharmaceutical"},
  {"s": "TITAN", "n": "Titan Company"},
  {"s": "ULTRACEMCO", "n": "UltraTech Cement"},
  {"s": "WIPRO", "n": "Wipro"},
  {"s": "NESTLEIND", "n": "Nestle India"},
  {"s": "ONGC", "n": "Oil & Natural Gas Corporation"},
  {"s": "NTPC", "n": "NTPC"},
  {"s": "POWERGRID", "n": "Power Grid Corporation"},
  {"s": "M&M", "n": "Mahindra & Mahindra"},
  {"s": "TATAMOTORS", "n": "Tata Motors"},
  {"s": "TATASTEEL", "n": "Tata Steel"},
  {"s": "JSWSTEEL", "n": "JSW Steel"},
  {"s": "ADANIENT", "n": "Adani Enterprises"},
  {"s": "ADANIPORTS", "n": "Adani Ports & SEZ"},
  {"s": "COALINDIA", "n": "Coal India"},
  {"s": "GRASIM", "n": "Grasim Industries"},
  {"s": "BAJAJFINSV", "n": "Bajaj Finserv"},
  {"s": "HDFCLIFE", "n": "HDFC Life Insurance"},
  {"s": "SBILIFE", "n": "SBI Life Insurance"},
  {"s": "BRITANNIA", "n": "Britannia Industries"},
  {"s": "DRREDDY", "n": "Dr. Reddy's Laboratories"},
  {"s": "CIPLA", "n": "Cipla"},
  {"s": "DIVISLAB", "n": "Divi's Laboratories"},
  {"s": "EICHERMOT", "n": "Eicher Motors"},
  {"s": "HEROMOTOCO", "n": "Hero MotoCorp"},
  {"s": "BAJAJ-AUTO", "n": "Bajaj Auto"},
  {"s": "INDUSINDBK", "n": "IndusInd Bank"},
  {"s": "TECHM", "n": "Tech Mahindra"},
  {"s": "APOLLOHOSP", "n": "Apollo Hospitals"},
  {"s": "TATACONSUM", "n": "Tata Consumer Products"},
  {"s": "BPCL", "n": "Bharat Petroleum"},
  {"s": "IOC", "n": "Indian Oil Corporation"},
  {"s": "HINDALCO", "n": "Hindalco Industries"},
  {"s": "SHREECEM", "n": "Shree Cement"},
  {"s": "PIDILITIND", "n": "Pidilite Industries"},
  {"s": "DABUR", "n": "Dabur India"},
  {"s": "GODREJCP", "n": "Godrej Consumer Products"},
  {"s": "MARICO", "n": "Marico"},
  {"s": "COLPAL", "n": "Colgate-Palmolive India"},
  {"s": "BERGEPAINT", "n": "Berger Paints"},
  {"s": "HAVELLS", "n": "Havells India"},
  {"s": "DLF", "n": "DLF"},
  {"s": "AMBUJACEM", "n": "Ambuja Cements"},
  {"s": "ACC", "n": "ACC"},
  {"s": "BANKBARODA", "n": "Bank of Baroda"},
  {"s": "PNB", "n": "Punjab National Bank"},
  {"s": "CANBK", "n": "Canara Bank"},
  {"s": "IDFCFIRSTB", "n": "IDFC First Bank"},
  {"s": "AUBANK", "n": "AU Small Finance Bank"},
  {"s": "FEDERALBNK", "n": "Federal Bank"},
  {"s": "CHOLAFIN", "n": "Cholamandalam Investment"},
  {"s": "MUTHOOTFIN", "n": "Muthoot Finance"},
  {"s": "ICICIPRULI", "n": "ICICI Prudential Life"},
  {"s": "ICICIGI", "n": "ICICI Lombard"},
  {"s": "HDFCAMC", "n": "HDFC Asset Management"},
  {"s": "SBICARD", "n": "SBI Cards & Payment"},
  {"s": "GAIL", "n": "GAIL India"},
  {"s": "PETRONET", "n": "Petronet LNG"},
  {"s": "IGL", "n": "Indraprastha Gas"},
  {"s": "TORNTPHARM", "n": "Torrent Pharmaceuticals"},
  {"s": "LUPIN", "n": "Lupin"},
  {"s": "AUROPHARMA", "n": "Aurobindo Pharma"},
  {"s": "BIOCON", "n": "Biocon"},
  {"s": "ALKEM", "n": "Alkem Laboratories"},
  {"s": "MOTHERSON", "n": "Samvardhana Motherson"},
  {"s": "BOSCHLTD", "n": "Bosch"},
  {"s": "BALKRISIND", "n": "Balkrishna Industries"},
  {"s": "MRF", "n": "MRF"},
  {"s": "ASHOKLEY", "n": "Ashok Leyland"},
  {"s": "TVSMOTOR", "n": "TVS Motor Company"},
  {"s": "SIEMENS", "n": "Siemens India"},
  {"s": "ABB", "n": "ABB India"},
  {"s": "BEL", "n": "Bharat Electronics"},
  {"s": "HAL", "n": "Hindustan Aeronautics"},
  {"s": "VEDL", "n": "Vedanta"},
  {"s": "NMDC", "n": "NMDC"},
  {"s": "SAIL", "n": "Steel Authority of India"},
  {"s": "JINDALSTEL", "n": "Jindal Steel & Power"},
  {"s": "NATIONALUM", "n": "National Aluminium"},
  {"s": "PAGEIND", "n": "Page Industries"},
  {"s": "TRENT", "n": "Trent"},
  {"s": "NAUKRI", "n": "Info Edge (Naukri)"},
  {"s": "DMART", "n": "Avenue Supermarts (DMart)"},
  {"s": "INDIGO", "n": "InterGlobe Aviation (IndiGo)"},
  {"s": "SRF", "n": "SRF"},
  {"s": "ZOMATO", "n": "Zomato / Eternal"},
  {"s": "PAYTM", "n": "One97 (Paytm)"},
  {"s": "NYKAA", "n": "FSN E-Commerce (Nykaa)"},
  {"s": "LTIM", "n": "LTIMindtree"},
  {"s": "PERSISTENT", "n": "Persistent Systems"},
  {"s": "COFORGE", "n": "Coforge"},
  {"s": "MPHASIS", "n": "Mphasis"},
  {"s": "POLYCAB", "n": "Polycab India"},
  {"s": "PIIND", "n": "PI Industries"},
  {"s": "DEEPAKNTR", "n": "Deepak Nitrite"},
  {"s": "TATAPOWER", "n": "Tata Power"},
  {"s": "ADANIGREEN", "n": "Adani Green Energy"},
  {"s": "ADANIPOWER", "n": "Adani Power"},
  {"s": "JIOFIN", "n": "Jio Financial Services"},
  {"s": "IRCTC", "n": "Indian Railway Catering (IRCTC)"},
  {"s": "IRFC", "n": "Indian Railway Finance"},
  {"s": "BANKNIFTY", "n": "Nifty Bank Index"},
  {"s": "^NSEI", "n": "Nifty 50 Index"}
]
